<annotation>
	<folder>Package9-Ivo</folder>
	<filename>cam_left0525.jpg</filename>
	<path>C:\Users\A675180\Cure\curenet\Training Data\FSOCO RAW\Package9-Ivo\cam_left0525.jpg</path>
	<source>
		<database>Unknown</database>
	</source>
	<size>
		<width>640</width>
		<height>480</height>
		<depth>3</depth>
	</size>
	<segmented>0</segmented>
	<object>
		<name>cone-blue</name>
		<pose>Unspecified</pose>
		<truncated>0</truncated>
		<difficult>0</difficult>
		<bndbox>
			<xmin>193</xmin>
			<ymin>211</ymin>
			<xmax>243</xmax>
			<ymax>274</ymax>
		</bndbox>
	</object>
	<object>
		<name>cone-blue</name>
		<pose>Unspecified</pose>
		<truncated>0</truncated>
		<difficult>0</difficult>
		<bndbox>
			<xmin>102</xmin>
			<ymin>224</ymin>
			<xmax>121</xmax>
			<ymax>250</ymax>
		</bndbox>
	</object>
	<object>
		<name>cone-blue</name>
		<pose>Unspecified</pose>
		<truncated>0</truncated>
		<difficult>0</difficult>
		<bndbox>
			<xmin>264</xmin>
			<ymin>224</ymin>
			<xmax>288</xmax>
			<ymax>256</ymax>
		</bndbox>
	</object>
	<object>
		<name>cone-yellow</name>
		<pose>Unspecified</pose>
		<truncated>0</truncated>
		<difficult>0</difficult>
		<bndbox>
			<xmin>248</xmin>
			<ymin>228</ymin>
			<xmax>259</xmax>
			<ymax>249</ymax>
		</bndbox>
	</object>
	<object>
		<name>cone-yellow</name>
		<pose>Unspecified</pose>
		<truncated>0</truncated>
		<difficult>0</difficult>
		<bndbox>
			<xmin>382</xmin>
			<ymin>226</ymin>
			<xmax>398</xmax>
			<ymax>248</ymax>
		</bndbox>
	</object>
	<object>
		<name>cone-yellow</name>
		<pose>Unspecified</pose>
		<truncated>0</truncated>
		<difficult>0</difficult>
		<bndbox>
			<xmin>574</xmin>
			<ymin>216</ymin>
			<xmax>602</xmax>
			<ymax>252</ymax>
		</bndbox>
	</object>
</annotation>
