<annotation>
    <folder>tmpmhbj3cwq</folder>
    <filename>cjtodfk3p3ol90988g9a515r7.jpeg</filename>
    <path>/tmp/tmpmhbj3cwq/cjtodfk3p3ol90988g9a515r7.jpeg</path>
    <source>
        <database>Unknown</database>
    </source>
    <size>
        <width>1280</width>
        <height>1024</height>
        <depth>3</depth>
    </size>
    <segmented>0</segmented>
    <object>
        <name>yellow-cone</name>
        <pose>Unspecified</pose>
        <truncated>0</truncated>
        <difficult>0</difficult>
        <polygon>
            <x1>1161</x1>
                <y1>727</y1>
            <x2>1204</x2>
                <y2>663</y2>
            <x3>1221</x3>
                <y3>732</y3>
            </polygon>
        </object>
    <object>
        <name>yellow-cone</name>
        <pose>Unspecified</pose>
        <truncated>0</truncated>
        <difficult>0</difficult>
        <polygon>
            <x1>1242</x1>
                <y1>648</y1>
            <x2>1264</x2>
                <y2>602</y2>
            <x3>1279</x3>
                <y3>656</y3>
            </polygon>
        </object>
    <object>
        <name>yellow-cone</name>
        <pose>Unspecified</pose>
        <truncated>0</truncated>
        <difficult>0</difficult>
        <polygon>
            <x1>1204</x1>
                <y1>885</y1>
            <x2>1275</x2>
                <y2>788</y2>
            <x3>1280</x3>
                <y3>927</y3>
            </polygon>
        </object>
    <object>
        <name>blue-cone</name>
        <pose>Unspecified</pose>
        <truncated>0</truncated>
        <difficult>0</difficult>
        <polygon>
            <x1>382</x1>
                <y1>636</y1>
            <x2>406</x2>
                <y2>581</y2>
            <x3>428</x3>
                <y3>634</y3>
            </polygon>
        </object>
    <object>
        <name>blue-cone</name>
        <pose>Unspecified</pose>
        <truncated>0</truncated>
        <difficult>0</difficult>
        <polygon>
            <x1>704</x1>
                <y1>595</y1>
            <x2>719</x2>
                <y2>558</y2>
            <x3>732</x3>
                <y3>596</y3>
            </polygon>
        </object>
    <object>
        <name>blue-cone</name>
        <pose>Unspecified</pose>
        <truncated>0</truncated>
        <difficult>0</difficult>
        <polygon>
            <x1>991</x1>
                <y1>582</y1>
            <x2>1005</x2>
                <y2>551</y2>
            <x3>1020</x3>
                <y3>586</y3>
            </polygon>
        </object>
    <object>
        <name>blue-cone</name>
        <pose>Unspecified</pose>
        <truncated>0</truncated>
        <difficult>0</difficult>
        <polygon>
            <x1>1258</x1>
                <y1>585</y1>
            <x2>1270</x2>
                <y2>555</y2>
            <x3>1279</x3>
                <y3>585</y3>
            </polygon>
        </object>
    </annotation>
