<annotation>
    <folder>tmpmhbj3cwq</folder>
    <filename>cjtohg2g45a7a0993dzx6a5w3.jpeg</filename>
    <path>/tmp/tmpmhbj3cwq/cjtohg2g45a7a0993dzx6a5w3.jpeg</path>
    <source>
        <database>Unknown</database>
    </source>
    <size>
        <width>1280</width>
        <height>1024</height>
        <depth>3</depth>
    </size>
    <segmented>0</segmented>
    <object>
        <name>yellow-cone</name>
        <pose>Unspecified</pose>
        <truncated>0</truncated>
        <difficult>0</difficult>
        <polygon>
            <x1>952</x1>
                <y1>695</y1>
            <x2>985</x2>
                <y2>627</y2>
            <x3>1016</x3>
                <y3>700</y3>
            </polygon>
        </object>
    <object>
        <name>yellow-cone</name>
        <pose>Unspecified</pose>
        <truncated>0</truncated>
        <difficult>0</difficult>
        <polygon>
            <x1>532</x1>
                <y1>614</y1>
            <x2>543</x2>
                <y2>573</y2>
            <x3>561</x3>
                <y3>616</y3>
            </polygon>
        </object>
    <object>
        <name>yellow-cone</name>
        <pose>Unspecified</pose>
        <truncated>0</truncated>
        <difficult>0</difficult>
        <polygon>
            <x1>304</x1>
                <y1>589</y1>
            <x2>313</x2>
                <y2>562</y2>
            <x3>325</x3>
                <y3>596</y3>
            </polygon>
        </object>
    <object>
        <name>yellow-cone</name>
        <pose>Unspecified</pose>
        <truncated>0</truncated>
        <difficult>0</difficult>
        <polygon>
            <x1>251</x1>
                <y1>567</y1>
            <x2>259</x2>
                <y2>546</y2>
            <x3>267</x3>
                <y3>569</y3>
            </polygon>
        </object>
    <object>
        <name>yellow-cone</name>
        <pose>Unspecified</pose>
        <truncated>0</truncated>
        <difficult>0</difficult>
        <polygon>
            <x1>1083</x1>
                <y1>564</y1>
            <x2>1093</x2>
                <y2>536</y2>
            <x3>1104</x3>
                <y3>567</y3>
            </polygon>
        </object>
    <object>
        <name>yellow-cone</name>
        <pose>Unspecified</pose>
        <truncated>0</truncated>
        <difficult>0</difficult>
        <polygon>
            <x1>854</x1>
                <y1>555</y1>
            <x2>859</x2>
                <y2>531</y2>
            <x3>870</x3>
                <y3>557</y3>
            </polygon>
        </object>
    <object>
        <name>yellow-cone</name>
        <pose>Unspecified</pose>
        <truncated>0</truncated>
        <difficult>0</difficult>
        <polygon>
            <x1>737</x1>
                <y1>539</y1>
            <x2>744</x2>
                <y2>522</y2>
            <x3>749</x3>
                <y3>537</y3>
            </polygon>
        </object>
    <object>
        <name>blue-cone</name>
        <pose>Unspecified</pose>
        <truncated>0</truncated>
        <difficult>0</difficult>
        <polygon>
            <x1>33</x1>
                <y1>687</y1>
            <x2>50</x2>
                <y2>630</y2>
            <x3>76</x3>
                <y3>684</y3>
            </polygon>
        </object>
    <object>
        <name>blue-cone</name>
        <pose>Unspecified</pose>
        <truncated>0</truncated>
        <difficult>0</difficult>
        <polygon>
            <x1>32</x1>
                <y1>569</y1>
            <x2>41</x2>
                <y2>551</y2>
            <x3>46</x3>
                <y3>570</y3>
            </polygon>
        </object>
    <object>
        <name>blue-cone</name>
        <pose>Unspecified</pose>
        <truncated>0</truncated>
        <difficult>0</difficult>
        <polygon>
            <x1>72</x1>
                <y1>951</y1>
            <x2>0</x2>
                <y2>817</y2>
            <x3>0</x3>
                <y3>936</y3>
            </polygon>
        </object>
    </annotation>
