{"tags": [], "description": "", "objects": [{"description": "", "bitmap": null, "tags": [], "classTitle": "blue", "points": {"exterior": [[175.0, 318.0], [310.0, 475.0]], "interior": []}}, {"description": "", "bitmap": null, "tags": [], "classTitle": "blue", "points": {"exterior": [[437.0, 196.0], [510.0, 275.0]], "interior": []}}, {"description": "", "bitmap": null, "tags": [], "classTitle": "blue", "points": {"exterior": [[427.0, 161.0], [472.0, 220.0]], "interior": []}}, {"description": "", "bitmap": null, "tags": [], "classTitle": "blue", "points": {"exterior": [[311.0, 146.0], [352.0, 198.0]], "interior": []}}, {"description": "", "bitmap": null, "tags": [], "classTitle": "blue", "points": {"exterior": [[163.0, 144.0], [205.0, 192.0]], "interior": []}}, {"description": "", "bitmap": null, "tags": [], "classTitle": "yellow", "points": {"exterior": [[318.0, 111.0], [348.0, 143.0]], "interior": []}}, {"description": "", "bitmap": null, "tags": [], "classTitle": "yellow", "points": {"exterior": [[453.0, 108.0], [479.0, 140.0]], "interior": []}}, {"description": "", "bitmap": null, "tags": [], "classTitle": "yellow", "points": {"exterior": [[656.0, 106.0], [681.0, 142.0]], "interior": []}}, {"description": "", "bitmap": null, "tags": [], "classTitle": "yellow", "points": {"exterior": [[823.0, 111.0], [850.0, 151.0]], "interior": []}}, {"description": "", "bitmap": null, "tags": [], "classTitle": "yellow", "points": {"exterior": [[1003.0, 136.0], [1039.0, 188.0]], "interior": []}}, {"description": "", "bitmap": null, "tags": [], "classTitle": "yellow", "points": {"exterior": [[1138.0, 169.0], [1194.0, 244.0]], "interior": []}}, {"description": "", "bitmap": null, "tags": [], "classTitle": "yellow", "points": {"exterior": [[1463.0, 235.0], [1559.0, 357.0]], "interior": []}}], "size": {"height": 552, "width": 2064}}