{"tags": [], "description": "", "objects": [{"description": "", "bitmap": null, "tags": [], "classTitle": "blue", "points": {"exterior": [[752.0, 88.0], [773.0, 113.0]], "interior": []}}, {"description": "", "bitmap": null, "tags": [], "classTitle": "blue", "points": {"exterior": [[883.0, 83.0], [902.0, 104.0]], "interior": []}}, {"description": "", "bitmap": null, "tags": [], "classTitle": "blue", "points": {"exterior": [[1010.0, 81.0], [1029.0, 102.0]], "interior": []}}, {"description": "", "bitmap": null, "tags": [], "classTitle": "blue", "points": {"exterior": [[1287.0, 87.0], [1309.0, 114.0]], "interior": []}}, {"description": "", "bitmap": null, "tags": [], "classTitle": "blue", "points": {"exterior": [[501.0, 101.0], [524.0, 131.0]], "interior": []}}, {"description": "", "bitmap": null, "tags": [], "classTitle": "blue", "points": {"exterior": [[632.0, 92.0], [652.0, 118.0]], "interior": []}}, {"description": "", "bitmap": null, "tags": [], "classTitle": "yellow", "points": {"exterior": [[781.0, 100.0], [814.0, 136.0]], "interior": []}}, {"description": "", "bitmap": null, "tags": [], "classTitle": "yellow", "points": {"exterior": [[862.0, 99.0], [885.0, 130.0]], "interior": []}}, {"description": "", "bitmap": null, "tags": [], "classTitle": "yellow", "points": {"exterior": [[959.0, 96.0], [984.0, 126.0]], "interior": []}}, {"description": "", "bitmap": null, "tags": [], "classTitle": "yellow", "points": {"exterior": [[1058.0, 96.0], [1078.0, 127.0]], "interior": []}}, {"description": "", "bitmap": null, "tags": [], "classTitle": "yellow", "points": {"exterior": [[1175.0, 102.0], [1201.0, 136.0]], "interior": []}}, {"description": "", "bitmap": null, "tags": [], "classTitle": "blue", "points": {"exterior": [[1466.0, 91.0], [1488.0, 122.0]], "interior": []}}, {"description": "", "bitmap": null, "tags": [], "classTitle": "yellow", "points": {"exterior": [[1328.0, 109.0], [1358.0, 149.0]], "interior": []}}, {"description": "", "bitmap": null, "tags": [], "classTitle": "blue", "points": {"exterior": [[1796.0, 103.0], [1835.0, 146.0]], "interior": []}}, {"description": "", "bitmap": null, "tags": [], "classTitle": "blue", "points": {"exterior": [[340.0, 124.0], [373.0, 162.0]], "interior": []}}, {"description": "", "bitmap": null, "tags": [], "classTitle": "yellow", "points": {"exterior": [[739.0, 120.0], [770.0, 160.0]], "interior": []}}, {"description": "", "bitmap": null, "tags": [], "classTitle": "yellow", "points": {"exterior": [[797.0, 131.0], [831.0, 177.0]], "interior": []}}, {"description": "", "bitmap": null, "tags": [], "classTitle": "yellow", "points": {"exterior": [[1659.0, 127.0], [1706.0, 179.0]], "interior": []}}, {"description": "", "bitmap": null, "tags": [], "classTitle": "blue", "points": {"exterior": [[248.0, 152.0], [295.0, 202.0]], "interior": []}}, {"description": "", "bitmap": null, "tags": [], "classTitle": "yellow", "points": {"exterior": [[1009.0, 153.0], [1059.0, 220.0]], "interior": []}}, {"description": "", "bitmap": null, "tags": [], "classTitle": "yellow", "points": {"exterior": [[1256.0, 185.0], [1327.0, 276.0]], "interior": []}}, {"description": "", "bitmap": null, "tags": [], "classTitle": "blue", "points": {"exterior": [[158.0, 298.0], [295.0, 443.0]], "interior": []}}, {"description": "", "bitmap": null, "tags": [], "classTitle": "yellow", "points": {"exterior": [[1724.0, 290.0], [1875.0, 455.0]], "interior": []}}, {"description": "", "bitmap": null, "tags": [], "classTitle": "blue", "points": {"exterior": [[256.0, 188.0], [316.0, 256.0]], "interior": []}}, {"description": "", "bitmap": null, "tags": [], "classTitle": "yellow", "points": {"exterior": [[731.0, 111.0], [755.0, 145.0]], "interior": []}}], "size": {"height": 552, "width": 2064}}