{"tags": [], "description": "", "objects": [{"description": "", "bitmap": null, "tags": [], "classTitle": "blue", "points": {"exterior": [[978.0, 72.0], [1016.0, 133.0]], "interior": []}}, {"description": "", "bitmap": null, "tags": [], "classTitle": "blue", "points": {"exterior": [[1349.0, 31.0], [1377.0, 72.0]], "interior": []}}, {"description": "", "bitmap": null, "tags": [], "classTitle": "blue", "points": {"exterior": [[1558.0, 13.0], [1583.0, 49.0]], "interior": []}}, {"description": "", "bitmap": null, "tags": [], "classTitle": "blue", "points": {"exterior": [[1855.0, 6.0], [1887.0, 45.0]], "interior": []}}, {"description": "", "bitmap": null, "tags": [], "classTitle": "yellow", "points": {"exterior": [[1984.0, 68.0], [2048.0, 140.0]], "interior": []}}, {"description": "", "bitmap": null, "tags": [], "classTitle": "yellow", "points": {"exterior": [[1800.0, 175.0], [1925.0, 314.0]], "interior": []}}], "size": {"height": 552, "width": 2064}}