<annotation><filename>frame4308.jpg</filename><folder>batch_72</folder><source><sourceImage>The MIT-CSAIL database of objects and scenes</sourceImage><sourceAnnotation>LabelMe Webtool</sourceAnnotation></source><object><name>blue</name><deleted>0</deleted><verified>0</verified><occluded>no</occluded><attributes></attributes><parts><hasparts></hasparts><ispartof></ispartof></parts><date>10-Jun-2018 09:44:35</date><id>0</id><type>bounding_box</type><polygon><username>anonymous</username><pt><x>302</x><y>177</y></pt><pt><x>330</x><y>177</y></pt><pt><x>330</x><y>134</y></pt><pt><x>302</x><y>134</y></pt></polygon></object><object><name>blue</name><deleted>0</deleted><verified>0</verified><occluded>no</occluded><attributes></attributes><parts><hasparts></hasparts><ispartof></ispartof></parts><date>10-Jun-2018 09:44:39</date><id>1</id><type>bounding_box</type><polygon><username>anonymous</username><pt><x>393</x><y>124</y></pt><pt><x>409</x><y>124</y></pt><pt><x>409</x><y>100</y></pt><pt><x>393</x><y>100</y></pt></polygon></object><object><name>b</name><deleted>1</deleted><verified>0</verified><occluded>no</occluded><attributes></attributes><parts><hasparts></hasparts><ispartof></ispartof></parts><date>10-Jun-2018 09:45:02</date><id>2</id><type>bounding_box</type><polygon><username>anonymous</username><pt><x>506</x><y>102</y></pt><pt><x>516</x><y>102</y></pt><pt><x>516</x><y>86</y></pt><pt><x>506</x><y>86</y></pt></polygon></object><object><name>blue</name><deleted>0</deleted><verified>0</verified><occluded>no</occluded><attributes></attributes><parts><hasparts></hasparts><ispartof></ispartof></parts><date>10-Jun-2018 09:45:09</date><id>3</id><type>bounding_box</type><polygon><username>anonymous</username><pt><x>507</x><y>103</y></pt><pt><x>516</x><y>103</y></pt><pt><x>516</x><y>86</y></pt><pt><x>507</x><y>86</y></pt></polygon></object><object><name>b</name><deleted>1</deleted><verified>0</verified><occluded>no</occluded><attributes></attributes><parts><hasparts></hasparts><ispartof></ispartof></parts><date>10-Jun-2018 09:45:12</date><id>4</id><type>bounding_box</type><polygon><username>anonymous</username><pt><x>569</x><y>94</y></pt><pt><x>578</x><y>94</y></pt><pt><x>578</x><y>81</y></pt><pt><x>569</x><y>81</y></pt></polygon></object><object><name>blue</name><deleted>0</deleted><verified>0</verified><occluded>no</occluded><attributes></attributes><parts><hasparts></hasparts><ispartof></ispartof></parts><date>10-Jun-2018 09:45:18</date><id>5</id><type>bounding_box</type><polygon><username>anonymous</username><pt><x>569</x><y>94</y></pt><pt><x>578</x><y>94</y></pt><pt><x>578</x><y>81</y></pt><pt><x>569</x><y>81</y></pt></polygon></object><object><name>yellow</name><deleted>0</deleted><verified>0</verified><occluded>no</occluded><attributes></attributes><parts><hasparts></hasparts><ispartof></ispartof></parts><date>10-Jun-2018 09:45:22</date><id>6</id><type>bounding_box</type><polygon><username>anonymous</username><pt><x>665</x><y>171</y></pt><pt><x>690</x><y>171</y></pt><pt><x>690</x><y>133</y></pt><pt><x>665</x><y>133</y></pt></polygon></object><object><name>yellow</name><deleted>0</deleted><verified>0</verified><occluded>no</occluded><attributes></attributes><parts><hasparts></hasparts><ispartof></ispartof></parts><date>10-Jun-2018 09:45:27</date><id>7</id><type>bounding_box</type><polygon><username>anonymous</username><pt><x>650</x><y>134</y></pt><pt><x>667</x><y>134</y></pt><pt><x>667</x><y>109</y></pt><pt><x>650</x><y>109</y></pt></polygon></object><object><name>yellow</name><deleted>0</deleted><verified>0</verified><occluded>no</occluded><attributes></attributes><parts><hasparts></hasparts><ispartof></ispartof></parts><date>10-Jun-2018 09:45:30</date><id>8</id><type>bounding_box</type><polygon><username>anonymous</username><pt><x>673</x><y>114</y></pt><pt><x>661</x><y>114</y></pt><pt><x>661</x><y>95</y></pt><pt><x>673</x><y>95</y></pt></polygon></object><object><name>yellow</name><deleted>0</deleted><verified>0</verified><occluded>no</occluded><attributes></attributes><parts><hasparts></hasparts><ispartof></ispartof></parts><date>10-Jun-2018 09:45:33</date><id>9</id><type>bounding_box</type><polygon><username>anonymous</username><pt><x>681</x><y>105</y></pt><pt><x>692</x><y>105</y></pt><pt><x>692</x><y>89</y></pt><pt><x>681</x><y>89</y></pt></polygon></object><object><name>yellow</name><deleted>0</deleted><verified>0</verified><occluded>no</occluded><attributes></attributes><parts><hasparts></hasparts><ispartof></ispartof></parts><date>10-Jun-2018 09:45:36</date><id>10</id><type>bounding_box</type><polygon><username>anonymous</username><pt><x>707</x><y>102</y></pt><pt><x>716</x><y>102</y></pt><pt><x>716</x><y>87</y></pt><pt><x>707</x><y>87</y></pt></polygon></object><object><name>yellow</name><deleted>0</deleted><verified>0</verified><occluded>no</occluded><attributes></attributes><parts><hasparts></hasparts><ispartof></ispartof></parts><date>10-Jun-2018 09:45:39</date><id>11</id><type>bounding_box</type><polygon><username>anonymous</username><pt><x>768</x><y>104</y></pt><pt><x>778</x><y>104</y></pt><pt><x>778</x><y>88</y></pt><pt><x>768</x><y>88</y></pt></polygon></object><object><name>yellow</name><deleted>0</deleted><verified>0</verified><occluded>no</occluded><attributes></attributes><parts><hasparts></hasparts><ispartof></ispartof></parts><date>10-Jun-2018 09:45:42</date><id>12</id><type>bounding_box</type><polygon><username>anonymous</username><pt><x>859</x><y>106</y></pt><pt><x>870</x><y>106</y></pt><pt><x>870</x><y>89</y></pt><pt><x>859</x><y>89</y></pt></polygon></object><object><name>yellow</name><deleted>0</deleted><verified>0</verified><occluded>no</occluded><attributes></attributes><parts><hasparts></hasparts><ispartof></ispartof></parts><date>10-Jun-2018 09:45:50</date><id>13</id><type>bounding_box</type><polygon><username>anonymous</username><pt><x>919</x><y>105</y></pt><pt><x>931</x><y>105</y></pt><pt><x>931</x><y>88</y></pt><pt><x>919</x><y>88</y></pt></polygon></object><object><name>yellow</name><deleted>0</deleted><verified>0</verified><occluded>no</occluded><attributes></attributes><parts><hasparts></hasparts><ispartof></ispartof></parts><date>10-Jun-2018 09:45:53</date><id>14</id><type>bounding_box</type><polygon><username>anonymous</username><pt><x>898</x><y>82</y></pt><pt><x>906</x><y>82</y></pt><pt><x>906</x><y>70</y></pt><pt><x>898</x><y>70</y></pt></polygon></object><object><name>blue</name><deleted>0</deleted><verified>0</verified><occluded>no</occluded><attributes></attributes><parts><hasparts></hasparts><ispartof></ispartof></parts><date>10-Jun-2018 09:45:59</date><id>15</id><type>bounding_box</type><polygon><username>anonymous</username><pt><x>622</x><y>88</y></pt><pt><x>629</x><y>88</y></pt><pt><x>629</x><y>76</y></pt><pt><x>622</x><y>76</y></pt></polygon></object><object><name>blue</name><deleted>0</deleted><verified>0</verified><occluded>no</occluded><attributes></attributes><parts><hasparts></hasparts><ispartof></ispartof></parts><date>10-Jun-2018 09:46:03</date><id>16</id><type>bounding_box</type><polygon><username>anonymous</username><pt><x>684</x><y>78</y></pt><pt><x>691</x><y>78</y></pt><pt><x>691</x><y>90</y></pt><pt><x>684</x><y>90</y></pt></polygon></object><object><name>blue</name><deleted>0</deleted><verified>0</verified><occluded>no</occluded><attributes></attributes><parts><hasparts></hasparts><ispartof></ispartof></parts><date>10-Jun-2018 09:46:07</date><id>17</id><type>bounding_box</type><polygon><username>anonymous</username><pt><x>728</x><y>89</y></pt><pt><x>735</x><y>89</y></pt><pt><x>735</x><y>77</y></pt><pt><x>728</x><y>77</y></pt></polygon></object><imagesize><nrows>256</nrows><ncols>960</ncols></imagesize></annotation>