<annotation><filename>frame5901.jpg</filename><folder>batch_231</folder><source><sourceImage>The MIT-CSAIL database of objects and scenes</sourceImage><sourceAnnotation>LabelMe Webtool</sourceAnnotation></source><object><name>orange_big</name><deleted>0</deleted><verified>0</verified><occluded>no</occluded><attributes></attributes><parts><hasparts></hasparts><ispartof></ispartof></parts><date>23-Jun-2018 11:51:10</date><id>0</id><type>bounding_box</type><polygon><username>anonymous</username><pt><x>7</x><y>116</y></pt><pt><x>33</x><y>116</y></pt><pt><x>33</x><y>76</y></pt><pt><x>7</x><y>76</y></pt></polygon></object><object><name>yellow</name><deleted>0</deleted><verified>0</verified><occluded>no</occluded><attributes></attributes><parts><hasparts></hasparts><ispartof></ispartof></parts><date>23-Jun-2018 11:51:15</date><id>1</id><type>bounding_box</type><polygon><username>anonymous</username><pt><x>10</x><y>66</y></pt><pt><x>21</x><y>66</y></pt><pt><x>21</x><y>79</y></pt><pt><x>10</x><y>79</y></pt></polygon></object><object><name>yellow</name><deleted>0</deleted><verified>0</verified><occluded>no</occluded><attributes></attributes><parts><hasparts></hasparts><ispartof></ispartof></parts><date>23-Jun-2018 11:51:20</date><id>2</id><type>bounding_box</type><polygon><username>anonymous</username><pt><x>26</x><y>86</y></pt><pt><x>39</x><y>86</y></pt><pt><x>39</x><y>70</y></pt><pt><x>26</x><y>70</y></pt></polygon></object><object><name>blue</name><deleted>0</deleted><verified>0</verified><occluded>no</occluded><attributes></attributes><parts><hasparts></hasparts><ispartof></ispartof></parts><date>23-Jun-2018 11:51:25</date><id>3</id><type>bounding_box</type><polygon><username>anonymous</username><pt><x>29</x><y>64</y></pt><pt><x>37</x><y>64</y></pt><pt><x>37</x><y>55</y></pt><pt><x>29</x><y>55</y></pt></polygon></object><object><name>yellow</name><deleted>0</deleted><verified>0</verified><occluded>no</occluded><attributes></attributes><parts><hasparts></hasparts><ispartof></ispartof></parts><date>23-Jun-2018 11:51:34</date><id>4</id><type>bounding_box</type><polygon><username>anonymous</username><pt><x>47</x><y>73</y></pt><pt><x>56</x><y>73</y></pt><pt><x>56</x><y>62</y></pt><pt><x>47</x><y>62</y></pt></polygon></object><object><name>orange_big</name><deleted>0</deleted><verified>0</verified><occluded>no</occluded><attributes></attributes><parts><hasparts></hasparts><ispartof></ispartof></parts><date>23-Jun-2018 11:51:39</date><id>5</id><type>bounding_box</type><polygon><username>anonymous</username><pt><x>73</x><y>89</y></pt><pt><x>90</x><y>89</y></pt><pt><x>90</x><y>63</y></pt><pt><x>73</x><y>63</y></pt></polygon></object><object><name>blue</name><deleted>0</deleted><verified>0</verified><occluded>no</occluded><attributes></attributes><parts><hasparts></hasparts><ispartof></ispartof></parts><date>23-Jun-2018 11:51:43</date><id>6</id><type>bounding_box</type><polygon><username>anonymous</username><pt><x>81</x><y>125</y></pt><pt><x>103</x><y>125</y></pt><pt><x>103</x><y>97</y></pt><pt><x>81</x><y>97</y></pt></polygon></object><object><name>yellow</name><deleted>0</deleted><verified>0</verified><occluded>no</occluded><attributes></attributes><parts><hasparts></hasparts><ispartof></ispartof></parts><date>23-Jun-2018 11:51:48</date><id>7</id><type>bounding_box</type><polygon><username>anonymous</username><pt><x>106</x><y>70</y></pt><pt><x>115</x><y>70</y></pt><pt><x>115</x><y>58</y></pt><pt><x>106</x><y>58</y></pt></polygon></object><object><name>yellow</name><deleted>0</deleted><verified>0</verified><occluded>no</occluded><attributes></attributes><parts><hasparts></hasparts><ispartof></ispartof></parts><date>23-Jun-2018 11:51:54</date><id>8</id><type>bounding_box</type><polygon><username>anonymous</username><pt><x>127</x><y>93</y></pt><pt><x>139</x><y>93</y></pt><pt><x>139</x><y>75</y></pt><pt><x>127</x><y>75</y></pt></polygon></object><object><name>blue</name><deleted>0</deleted><verified>0</verified><occluded>no</occluded><attributes></attributes><parts><hasparts></hasparts><ispartof></ispartof></parts><date>23-Jun-2018 11:51:58</date><id>9</id><type>bounding_box</type><polygon><username>anonymous</username><pt><x>134</x><y>62</y></pt><pt><x>140</x><y>62</y></pt><pt><x>140</x><y>54</y></pt><pt><x>134</x><y>54</y></pt></polygon></object><object><name>yellow</name><deleted>0</deleted><verified>0</verified><occluded>no</occluded><attributes></attributes><parts><hasparts></hasparts><ispartof></ispartof></parts><date>23-Jun-2018 11:52:10</date><id>10</id><type>bounding_box</type><polygon><username>anonymous</username><pt><x>176</x><y>68</y></pt><pt><x>184</x><y>68</y></pt><pt><x>184</x><y>59</y></pt><pt><x>176</x><y>59</y></pt></polygon></object><object><name>blue</name><deleted>0</deleted><verified>0</verified><occluded>no</occluded><attributes></attributes><parts><hasparts></hasparts><ispartof></ispartof></parts><date>23-Jun-2018 11:52:15</date><id>11</id><type>bounding_box</type><polygon><username>anonymous</username><pt><x>158</x><y>164</y></pt><pt><x>189</x><y>164</y></pt><pt><x>189</x><y>124</y></pt><pt><x>158</x><y>124</y></pt></polygon></object><object><name>orange_big</name><deleted>0</deleted><verified>0</verified><occluded>no</occluded><attributes></attributes><parts><hasparts></hasparts><ispartof></ispartof></parts><date>23-Jun-2018 11:52:20</date><id>12</id><type>bounding_box</type><polygon><username>anonymous</username><pt><x>204</x><y>95</y></pt><pt><x>222</x><y>95</y></pt><pt><x>222</x><y>67</y></pt><pt><x>204</x><y>67</y></pt></polygon></object><object><name>blue</name><deleted>0</deleted><verified>0</verified><occluded>no</occluded><attributes></attributes><parts><hasparts></hasparts><ispartof></ispartof></parts><date>23-Jun-2018 11:52:25</date><id>13</id><type>bounding_box</type><polygon><username>anonymous</username><pt><x>226</x><y>63</y></pt><pt><x>232</x><y>63</y></pt><pt><x>232</x><y>56</y></pt><pt><x>226</x><y>56</y></pt></polygon></object><object><name>yellow</name><deleted>0</deleted><verified>0</verified><occluded>no</occluded><attributes></attributes><parts><hasparts></hasparts><ispartof></ispartof></parts><date>23-Jun-2018 11:52:29</date><id>14</id><type>bounding_box</type><polygon><username>anonymous</username><pt><x>245</x><y>67</y></pt><pt><x>252</x><y>67</y></pt><pt><x>252</x><y>59</y></pt><pt><x>245</x><y>59</y></pt></polygon></object><object><name>yellow</name><deleted>0</deleted><verified>0</verified><occluded>no</occluded><attributes></attributes><parts><hasparts></hasparts><ispartof></ispartof></parts><date>23-Jun-2018 11:52:32</date><id>15</id><type>bounding_box</type><polygon><username>anonymous</username><pt><x>279</x><y>96</y></pt><pt><x>292</x><y>96</y></pt><pt><x>292</x><y>79</y></pt><pt><x>279</x><y>79</y></pt></polygon></object><object><name>yellow</name><deleted>0</deleted><verified>0</verified><occluded>no</occluded><attributes></attributes><parts><hasparts></hasparts><ispartof></ispartof></parts><date>23-Jun-2018 11:52:44</date><id>16</id><type>bounding_box</type><polygon><username>anonymous</username><pt><x>381</x><y>69</y></pt><pt><x>388</x><y>69</y></pt><pt><x>388</x><y>60</y></pt><pt><x>381</x><y>60</y></pt></polygon></object><object><name>blue</name><deleted>0</deleted><verified>0</verified><occluded>no</occluded><attributes></attributes><parts><hasparts></hasparts><ispartof></ispartof></parts><date>23-Jun-2018 11:52:48</date><id>17</id><type>bounding_box</type><polygon><username>anonymous</username><pt><x>402</x><y>66</y></pt><pt><x>407</x><y>66</y></pt><pt><x>407</x><y>59</y></pt><pt><x>402</x><y>59</y></pt></polygon></object><object><name>yellow</name><deleted>0</deleted><verified>0</verified><occluded>no</occluded><attributes></attributes><parts><hasparts></hasparts><ispartof></ispartof></parts><date>23-Jun-2018 11:52:53</date><id>18</id><type>bounding_box</type><polygon><username>anonymous</username><pt><x>415</x><y>94</y></pt><pt><x>427</x><y>94</y></pt><pt><x>427</x><y>77</y></pt><pt><x>415</x><y>77</y></pt></polygon></object><object><name>yellow</name><deleted>1</deleted><verified>0</verified><occluded>no</occluded><attributes></attributes><parts><hasparts></hasparts><ispartof></ispartof></parts><date>23-Jun-2018 11:52:58</date><id>19</id><type>bounding_box</type><polygon><username>anonymous</username><pt><x>440</x><y>70</y></pt><pt><x>446</x><y>70</y></pt><pt><x>446</x><y>62</y></pt><pt><x>440</x><y>62</y></pt></polygon></object><object><name>yellow</name><deleted>0</deleted><verified>0</verified><occluded>no</occluded><attributes></attributes><parts><hasparts></hasparts><ispartof></ispartof></parts><date>23-Jun-2018 11:53:06</date><id>20</id><type>bounding_box</type><polygon><username>anonymous</username><pt><x>489</x><y>74</y></pt><pt><x>495</x><y>74</y></pt><pt><x>495</x><y>65</y></pt><pt><x>489</x><y>65</y></pt></polygon></object><object><name>yellow</name><deleted>0</deleted><verified>0</verified><occluded>no</occluded><attributes></attributes><parts><hasparts></hasparts><ispartof></ispartof></parts><date>23-Jun-2018 11:53:12</date><id>21</id><type>bounding_box</type><polygon><username>anonymous</username><pt><x>479</x><y>133</y></pt><pt><x>497</x><y>133</y></pt><pt><x>497</x><y>104</y></pt><pt><x>479</x><y>104</y></pt></polygon></object><object><name>yellow</name><deleted>0</deleted><verified>0</verified><occluded>no</occluded><attributes></attributes><parts><hasparts></hasparts><ispartof></ispartof></parts><date>23-Jun-2018 11:53:16</date><id>22</id><type>bounding_box</type><polygon><username>anonymous</username><pt><x>496</x><y>88</y></pt><pt><x>505</x><y>88</y></pt><pt><x>505</x><y>75</y></pt><pt><x>496</x><y>75</y></pt></polygon></object><object><name>blue</name><deleted>0</deleted><verified>0</verified><occluded>no</occluded><attributes></attributes><parts><hasparts></hasparts><ispartof></ispartof></parts><date>23-Jun-2018 11:53:20</date><id>23</id><type>bounding_box</type><polygon><username>anonymous</username><pt><x>501</x><y>109</y></pt><pt><x>516</x><y>109</y></pt><pt><x>516</x><y>87</y></pt><pt><x>501</x><y>87</y></pt></polygon></object><object><name>yellow</name><deleted>0</deleted><verified>0</verified><occluded>no</occluded><attributes></attributes><parts><hasparts></hasparts><ispartof></ispartof></parts><date>23-Jun-2018 11:53:26</date><id>24</id><type>bounding_box</type><polygon><username>anonymous</username><pt><x>519</x><y>77</y></pt><pt><x>526</x><y>77</y></pt><pt><x>526</x><y>67</y></pt><pt><x>519</x><y>67</y></pt></polygon></object><object><name>yellow</name><deleted>0</deleted><verified>0</verified><occluded>no</occluded><attributes></attributes><parts><hasparts></hasparts><ispartof></ispartof></parts><date>23-Jun-2018 11:53:30</date><id>25</id><type>bounding_box</type><polygon><username>anonymous</username><pt><x>527</x><y>83</y></pt><pt><x>535</x><y>83</y></pt><pt><x>535</x><y>71</y></pt><pt><x>527</x><y>71</y></pt></polygon></object><object><name>blue</name><deleted>0</deleted><verified>0</verified><occluded>no</occluded><attributes></attributes><parts><hasparts></hasparts><ispartof></ispartof></parts><date>23-Jun-2018 11:53:34</date><id>26</id><type>bounding_box</type><polygon><username>anonymous</username><pt><x>546</x><y>72</y></pt><pt><x>552</x><y>72</y></pt><pt><x>552</x><y>64</y></pt><pt><x>546</x><y>64</y></pt></polygon></object><object><name>blue</name><deleted>0</deleted><verified>0</verified><occluded>no</occluded><attributes></attributes><parts><hasparts></hasparts><ispartof></ispartof></parts><date>23-Jun-2018 11:53:44</date><id>27</id><type>bounding_box</type><polygon><username>anonymous</username><pt><x>601</x><y>77</y></pt><pt><x>607</x><y>77</y></pt><pt><x>607</x><y>68</y></pt><pt><x>601</x><y>68</y></pt></polygon></object><object><name>blue</name><deleted>0</deleted><verified>0</verified><occluded>no</occluded><attributes></attributes><parts><hasparts></hasparts><ispartof></ispartof></parts><date>23-Jun-2018 11:53:48</date><id>28</id><type>bounding_box</type><polygon><username>anonymous</username><pt><x>616</x><y>95</y></pt><pt><x>626</x><y>95</y></pt><pt><x>626</x><y>80</y></pt><pt><x>616</x><y>80</y></pt></polygon></object><object><name>blue</name><deleted>0</deleted><verified>0</verified><occluded>no</occluded><attributes></attributes><parts><hasparts></hasparts><ispartof></ispartof></parts><date>23-Jun-2018 11:53:53</date><id>29</id><type>bounding_box</type><polygon><username>anonymous</username><pt><x>632</x><y>85</y></pt><pt><x>640</x><y>85</y></pt><pt><x>640</x><y>72</y></pt><pt><x>632</x><y>72</y></pt></polygon></object><object><name>orange small</name><deleted>0</deleted><verified>0</verified><occluded>no</occluded><attributes></attributes><parts><hasparts></hasparts><ispartof></ispartof></parts><date>23-Jun-2018 11:53:57</date><id>30</id><type>bounding_box</type><polygon><username>anonymous</username><pt><x>629</x><y>112</y></pt><pt><x>645</x><y>112</y></pt><pt><x>645</x><y>91</y></pt><pt><x>629</x><y>91</y></pt></polygon></object><object><name>orange small</name><deleted>0</deleted><verified>0</verified><occluded>no</occluded><attributes></attributes><parts><hasparts></hasparts><ispartof></ispartof></parts><date>23-Jun-2018 11:54:01</date><id>31</id><type>bounding_box</type><polygon><username>anonymous</username><pt><x>655</x><y>140</y></pt><pt><x>678</x><y>140</y></pt><pt><x>678</x><y>110</y></pt><pt><x>655</x><y>110</y></pt></polygon></object><object><name>orange small</name><deleted>0</deleted><verified>0</verified><occluded>no</occluded><attributes></attributes><parts><hasparts></hasparts><ispartof></ispartof></parts><date>23-Jun-2018 11:54:06</date><id>32</id><type>bounding_box</type><polygon><username>anonymous</username><pt><x>743</x><y>116</y></pt><pt><x>760</x><y>116</y></pt><pt><x>760</x><y>95</y></pt><pt><x>743</x><y>95</y></pt></polygon></object><object><name>orange small</name><deleted>0</deleted><verified>0</verified><occluded>no</occluded><attributes></attributes><parts><hasparts></hasparts><ispartof></ispartof></parts><date>23-Jun-2018 11:54:11</date><id>33</id><type>bounding_box</type><polygon><username>anonymous</username><pt><x>851</x><y>150</y></pt><pt><x>824</x><y>150</y></pt><pt><x>824</x><y>117</y></pt><pt><x>851</x><y>117</y></pt></polygon></object><object><name>yellow</name><deleted>0</deleted><verified>0</verified><occluded>no</occluded><attributes></attributes><parts><hasparts></hasparts><ispartof></ispartof></parts><date>23-Jun-2018 11:54:16</date><id>34</id><type>bounding_box</type><polygon><username>anonymous</username><pt><x>883</x><y>253</y></pt><pt><x>828</x><y>253</y></pt><pt><x>828</x><y>191</y></pt><pt><x>883</x><y>191</y></pt></polygon></object><imagesize><nrows>256</nrows><ncols>960</ncols></imagesize></annotation>