<annotation><filename>frame3989.jpg</filename><folder>batch_40</folder><source><sourceImage>The MIT-CSAIL database of objects and scenes</sourceImage><sourceAnnotation>LabelMe Webtool</sourceAnnotation></source><object><name>blue</name><deleted>1</deleted><verified>0</verified><occluded>no</occluded><attributes></attributes><parts><hasparts></hasparts><ispartof></ispartof></parts><date>07-Jun-2018 14:46:59</date><id>0</id><type>bounding_box</type><polygon><username>anonymous</username><pt><x>12</x><y>48</y></pt><pt><x>6</x><y>48</y></pt><pt><x>6</x><y>55</y></pt><pt><x>12</x><y>55</y></pt></polygon></object><object><name>blue</name><deleted>1</deleted><verified>0</verified><occluded>no</occluded><attributes></attributes><parts><hasparts></hasparts><ispartof></ispartof></parts><date>07-Jun-2018 14:47:06</date><id>1</id><type>bounding_box</type><polygon><username>anonymous</username><pt><x>13</x><y>48</y></pt><pt><x>4</x><y>48</y></pt><pt><x>4</x><y>56</y></pt><pt><x>13</x><y>56</y></pt></polygon></object><object><name>blue</name><deleted>1</deleted><verified>0</verified><occluded>no</occluded><attributes></attributes><parts><hasparts></hasparts><ispartof></ispartof></parts><date>07-Jun-2018 14:47:11</date><id>2</id><type>bounding_box</type><polygon><username>anonymous</username><pt><x>39</x><y>47</y></pt><pt><x>32</x><y>47</y></pt><pt><x>32</x><y>56</y></pt><pt><x>39</x><y>56</y></pt></polygon></object><object><name>blue</name><deleted>1</deleted><verified>0</verified><occluded>no</occluded><attributes></attributes><parts><hasparts></hasparts><ispartof></ispartof></parts><date>07-Jun-2018 14:47:15</date><id>3</id><type>bounding_box</type><polygon><username>anonymous</username><pt><x>52</x><y>49</y></pt><pt><x>44</x><y>49</y></pt><pt><x>44</x><y>57</y></pt><pt><x>52</x><y>57</y></pt></polygon></object><object><name>blue</name><deleted>1</deleted><verified>0</verified><occluded>no</occluded><attributes></attributes><parts><hasparts></hasparts><ispartof></ispartof></parts><date>07-Jun-2018 14:47:19</date><id>4</id><type>bounding_box</type><polygon><username>anonymous</username><pt><x>65</x><y>49</y></pt><pt><x>58</x><y>49</y></pt><pt><x>58</x><y>56</y></pt><pt><x>65</x><y>56</y></pt></polygon></object><object><name>yellow</name><deleted>0</deleted><verified>0</verified><occluded>no</occluded><attributes></attributes><parts><hasparts></hasparts><ispartof></ispartof></parts><date>07-Jun-2018 14:47:43</date><id>5</id><type>bounding_box</type><polygon><username>anonymous</username><pt><x>84</x><y>50</y></pt><pt><x>91</x><y>50</y></pt><pt><x>91</x><y>57</y></pt><pt><x>84</x><y>57</y></pt></polygon></object><object><name>yellow</name><deleted>0</deleted><verified>0</verified><occluded>no</occluded><attributes></attributes><parts><hasparts></hasparts><ispartof></ispartof></parts><date>07-Jun-2018 14:47:54</date><id>6</id><type>bounding_box</type><polygon><username>anonymous</username><pt><x>97</x><y>51</y></pt><pt><x>92</x><y>51</y></pt><pt><x>92</x><y>58</y></pt><pt><x>97</x><y>58</y></pt></polygon></object><object><name>yellow</name><deleted>0</deleted><verified>0</verified><occluded>no</occluded><attributes></attributes><parts><hasparts></hasparts><ispartof></ispartof></parts><date>07-Jun-2018 14:48:00</date><id>7</id><type>bounding_box</type><polygon><username>anonymous</username><pt><x>100</x><y>52</y></pt><pt><x>96</x><y>52</y></pt><pt><x>96</x><y>59</y></pt><pt><x>100</x><y>59</y></pt></polygon></object><object><name>yellow</name><deleted>0</deleted><verified>0</verified><occluded>no</occluded><attributes></attributes><parts><hasparts></hasparts><ispartof></ispartof></parts><date>07-Jun-2018 14:48:04</date><id>8</id><type>bounding_box</type><polygon><username>anonymous</username><pt><x>103</x><y>56</y></pt><pt><x>96</x><y>56</y></pt><pt><x>96</x><y>64</y></pt><pt><x>103</x><y>64</y></pt></polygon></object><object><name>yellow</name><deleted>0</deleted><verified>0</verified><occluded>no</occluded><attributes></attributes><parts><hasparts></hasparts><ispartof></ispartof></parts><date>07-Jun-2018 14:48:11</date><id>9</id><type>bounding_box</type><polygon><username>anonymous</username><pt><x>85</x><y>58</y></pt><pt><x>93</x><y>58</y></pt><pt><x>93</x><y>67</y></pt><pt><x>85</x><y>67</y></pt></polygon></object><object><name>blue</name><deleted>0</deleted><verified>0</verified><occluded>no</occluded><attributes></attributes><parts><hasparts></hasparts><ispartof></ispartof></parts><date>07-Jun-2018 14:48:18</date><id>10</id><type>bounding_box</type><polygon><username>anonymous</username><pt><x>155</x><y>65</y></pt><pt><x>146</x><y>65</y></pt><pt><x>146</x><y>74</y></pt><pt><x>155</x><y>74</y></pt></polygon></object><object><name>blue</name><deleted>0</deleted><verified>0</verified><occluded>no</occluded><attributes></attributes><parts><hasparts></hasparts><ispartof></ispartof></parts><date>07-Jun-2018 14:48:23</date><id>11</id><type>bounding_box</type><polygon><username>anonymous</username><pt><x>149</x><y>51</y></pt><pt><x>142</x><y>51</y></pt><pt><x>142</x><y>58</y></pt><pt><x>149</x><y>58</y></pt></polygon></object><object><name>blue</name><deleted>0</deleted><verified>0</verified><occluded>no</occluded><attributes></attributes><parts><hasparts></hasparts><ispartof></ispartof></parts><date>07-Jun-2018 14:48:28</date><id>12</id><type>bounding_box</type><polygon><username>anonymous</username><pt><x>155</x><y>52</y></pt><pt><x>149</x><y>52</y></pt><pt><x>149</x><y>59</y></pt><pt><x>155</x><y>59</y></pt></polygon></object><object><name>blue</name><deleted>0</deleted><verified>0</verified><occluded>no</occluded><attributes></attributes><parts><hasparts></hasparts><ispartof></ispartof></parts><date>07-Jun-2018 14:48:31</date><id>13</id><type>bounding_box</type><polygon><username>anonymous</username><pt><x>162</x><y>53</y></pt><pt><x>155</x><y>53</y></pt><pt><x>155</x><y>61</y></pt><pt><x>162</x><y>61</y></pt></polygon></object><object><name>blue</name><deleted>0</deleted><verified>0</verified><occluded>no</occluded><attributes></attributes><parts><hasparts></hasparts><ispartof></ispartof></parts><date>07-Jun-2018 14:48:39</date><id>14</id><type>bounding_box</type><polygon><username>anonymous</username><pt><x>166</x><y>55</y></pt><pt><x>161</x><y>55</y></pt><pt><x>161</x><y>63</y></pt><pt><x>166</x><y>63</y></pt></polygon></object><object><name>blue</name><deleted>0</deleted><verified>0</verified><occluded>no</occluded><attributes></attributes><parts><hasparts></hasparts><ispartof></ispartof></parts><date>07-Jun-2018 14:48:43</date><id>15</id><type>bounding_box</type><polygon><username>anonymous</username><pt><x>172</x><y>57</y></pt><pt><x>165</x><y>57</y></pt><pt><x>165</x><y>65</y></pt><pt><x>172</x><y>65</y></pt></polygon></object><object><name>blue</name><deleted>0</deleted><verified>0</verified><occluded>no</occluded><attributes></attributes><parts><hasparts></hasparts><ispartof></ispartof></parts><date>07-Jun-2018 14:48:47</date><id>16</id><type>bounding_box</type><polygon><username>anonymous</username><pt><x>182</x><y>60</y></pt><pt><x>175</x><y>60</y></pt><pt><x>175</x><y>68</y></pt><pt><x>182</x><y>68</y></pt></polygon></object><object><name>yellow</name><deleted>0</deleted><verified>0</verified><occluded>no</occluded><attributes></attributes><parts><hasparts></hasparts><ispartof></ispartof></parts><date>07-Jun-2018 14:48:51</date><id>17</id><type>bounding_box</type><polygon><username>anonymous</username><pt><x>184</x><y>65</y></pt><pt><x>177</x><y>65</y></pt><pt><x>177</x><y>74</y></pt><pt><x>184</x><y>74</y></pt></polygon></object><object><name>blue</name><deleted>0</deleted><verified>0</verified><occluded>no</occluded><attributes></attributes><parts><hasparts></hasparts><ispartof></ispartof></parts><date>07-Jun-2018 14:48:57</date><id>18</id><type>bounding_box</type><polygon><username>anonymous</username><pt><x>171</x><y>66</y></pt><pt><x>163</x><y>66</y></pt><pt><x>163</x><y>75</y></pt><pt><x>171</x><y>75</y></pt></polygon></object><object><name>blue</name><deleted>0</deleted><verified>0</verified><occluded>no</occluded><attributes></attributes><parts><hasparts></hasparts><ispartof></ispartof></parts><date>07-Jun-2018 14:49:03</date><id>19</id><type>bounding_box</type><polygon><username>anonymous</username><pt><x>200</x><y>67</y></pt><pt><x>192</x><y>67</y></pt><pt><x>192</x><y>75</y></pt><pt><x>200</x><y>75</y></pt></polygon></object><object><name>blue</name><deleted>0</deleted><verified>0</verified><occluded>no</occluded><attributes></attributes><parts><hasparts></hasparts><ispartof></ispartof></parts><date>07-Jun-2018 14:49:07</date><id>20</id><type>bounding_box</type><polygon><username>anonymous</username><pt><x>202</x><y>62</y></pt><pt><x>195</x><y>62</y></pt><pt><x>195</x><y>69</y></pt><pt><x>202</x><y>69</y></pt></polygon></object><object><name>blue</name><deleted>0</deleted><verified>0</verified><occluded>no</occluded><attributes></attributes><parts><hasparts></hasparts><ispartof></ispartof></parts><date>07-Jun-2018 14:49:10</date><id>21</id><type>bounding_box</type><polygon><username>anonymous</username><pt><x>215</x><y>66</y></pt><pt><x>207</x><y>66</y></pt><pt><x>207</x><y>74</y></pt><pt><x>215</x><y>74</y></pt></polygon></object><object><name>yellow</name><deleted>0</deleted><verified>0</verified><occluded>no</occluded><attributes></attributes><parts><hasparts></hasparts><ispartof></ispartof></parts><date>07-Jun-2018 14:49:15</date><id>22</id><type>bounding_box</type><polygon><username>anonymous</username><pt><x>225</x><y>66</y></pt><pt><x>218</x><y>66</y></pt><pt><x>218</x><y>74</y></pt><pt><x>225</x><y>74</y></pt></polygon></object><object><name>blue</name><deleted>0</deleted><verified>0</verified><occluded>no</occluded><attributes></attributes><parts><hasparts></hasparts><ispartof></ispartof></parts><date>07-Jun-2018 14:49:18</date><id>23</id><type>bounding_box</type><polygon><username>anonymous</username><pt><x>230</x><y>63</y></pt><pt><x>225</x><y>63</y></pt><pt><x>225</x><y>70</y></pt><pt><x>230</x><y>70</y></pt></polygon></object><object><name>blue</name><deleted>0</deleted><verified>0</verified><occluded>no</occluded><attributes></attributes><parts><hasparts></hasparts><ispartof></ispartof></parts><date>07-Jun-2018 14:49:24</date><id>24</id><type>bounding_box</type><polygon><username>anonymous</username><pt><x>258</x><y>63</y></pt><pt><x>251</x><y>63</y></pt><pt><x>251</x><y>71</y></pt><pt><x>258</x><y>71</y></pt></polygon></object><object><name>yellow</name><deleted>0</deleted><verified>0</verified><occluded>no</occluded><attributes></attributes><parts><hasparts></hasparts><ispartof></ispartof></parts><date>07-Jun-2018 14:49:29</date><id>25</id><type>bounding_box</type><polygon><username>anonymous</username><pt><x>275</x><y>67</y></pt><pt><x>267</x><y>67</y></pt><pt><x>267</x><y>77</y></pt><pt><x>275</x><y>77</y></pt></polygon></object><object><name>yellow</name><deleted>0</deleted><verified>0</verified><occluded>no</occluded><attributes></attributes><parts><hasparts></hasparts><ispartof></ispartof></parts><date>07-Jun-2018 14:49:34</date><id>26</id><type>bounding_box</type><polygon><username>anonymous</username><pt><x>315</x><y>68</y></pt><pt><x>306</x><y>68</y></pt><pt><x>306</x><y>79</y></pt><pt><x>315</x><y>79</y></pt></polygon></object><object><name>blue</name><deleted>0</deleted><verified>0</verified><occluded>no</occluded><attributes></attributes><parts><hasparts></hasparts><ispartof></ispartof></parts><date>07-Jun-2018 14:49:38</date><id>27</id><type>bounding_box</type><polygon><username>anonymous</username><pt><x>323</x><y>64</y></pt><pt><x>315</x><y>64</y></pt><pt><x>315</x><y>74</y></pt><pt><x>323</x><y>74</y></pt></polygon></object><object><name>yellow</name><deleted>0</deleted><verified>0</verified><occluded>no</occluded><attributes></attributes><parts><hasparts></hasparts><ispartof></ispartof></parts><date>07-Jun-2018 14:49:42</date><id>28</id><type>bounding_box</type><polygon><username>anonymous</username><pt><x>350</x><y>69</y></pt><pt><x>340</x><y>69</y></pt><pt><x>340</x><y>80</y></pt><pt><x>350</x><y>80</y></pt></polygon></object><object><name>blue</name><deleted>0</deleted><verified>0</verified><occluded>no</occluded><attributes></attributes><parts><hasparts></hasparts><ispartof></ispartof></parts><date>07-Jun-2018 14:49:47</date><id>29</id><type>bounding_box</type><polygon><username>anonymous</username><pt><x>377</x><y>67</y></pt><pt><x>369</x><y>67</y></pt><pt><x>369</x><y>76</y></pt><pt><x>377</x><y>76</y></pt></polygon></object><object><name>yellow</name><deleted>0</deleted><verified>0</verified><occluded>no</occluded><attributes></attributes><parts><hasparts></hasparts><ispartof></ispartof></parts><date>07-Jun-2018 14:49:51</date><id>30</id><type>bounding_box</type><polygon><username>anonymous</username><pt><x>398</x><y>72</y></pt><pt><x>387</x><y>72</y></pt><pt><x>387</x><y>84</y></pt><pt><x>398</x><y>84</y></pt></polygon></object><object><name>blue</name><deleted>0</deleted><verified>0</verified><occluded>no</occluded><attributes></attributes><parts><hasparts></hasparts><ispartof></ispartof></parts><date>07-Jun-2018 14:49:57</date><id>31</id><type>bounding_box</type><polygon><username>anonymous</username><pt><x>425</x><y>69</y></pt><pt><x>418</x><y>69</y></pt><pt><x>418</x><y>78</y></pt><pt><x>425</x><y>78</y></pt></polygon></object><object><name>yellow</name><deleted>0</deleted><verified>0</verified><occluded>no</occluded><attributes></attributes><parts><hasparts></hasparts><ispartof></ispartof></parts><date>07-Jun-2018 14:50:03</date><id>32</id><type>bounding_box</type><polygon><username>anonymous</username><pt><x>457</x><y>76</y></pt><pt><x>448</x><y>76</y></pt><pt><x>448</x><y>89</y></pt><pt><x>457</x><y>89</y></pt></polygon></object><object><name>blue</name><deleted>0</deleted><verified>0</verified><occluded>no</occluded><attributes></attributes><parts><hasparts></hasparts><ispartof></ispartof></parts><date>07-Jun-2018 14:50:08</date><id>33</id><type>bounding_box</type><polygon><username>anonymous</username><pt><x>473</x><y>72</y></pt><pt><x>464</x><y>72</y></pt><pt><x>464</x><y>83</y></pt><pt><x>473</x><y>83</y></pt></polygon></object><object><name>blue</name><deleted>0</deleted><verified>0</verified><occluded>no</occluded><attributes></attributes><parts><hasparts></hasparts><ispartof></ispartof></parts><date>07-Jun-2018 14:50:13</date><id>34</id><type>bounding_box</type><polygon><username>anonymous</username><pt><x>530</x><y>76</y></pt><pt><x>522</x><y>76</y></pt><pt><x>522</x><y>89</y></pt><pt><x>530</x><y>89</y></pt></polygon></object><object><name>yellow</name><deleted>0</deleted><verified>0</verified><occluded>no</occluded><attributes></attributes><parts><hasparts></hasparts><ispartof></ispartof></parts><date>07-Jun-2018 14:50:19</date><id>35</id><type>bounding_box</type><polygon><username>anonymous</username><pt><x>546</x><y>85</y></pt><pt><x>533</x><y>85</y></pt><pt><x>533</x><y>101</y></pt><pt><x>546</x><y>101</y></pt></polygon></object><object><name>blue</name><deleted>0</deleted><verified>0</verified><occluded>no</occluded><attributes></attributes><parts><hasparts></hasparts><ispartof></ispartof></parts><date>07-Jun-2018 14:50:26</date><id>36</id><type>bounding_box</type><polygon><username>anonymous</username><pt><x>635</x><y>85</y></pt><pt><x>623</x><y>85</y></pt><pt><x>623</x><y>99</y></pt><pt><x>635</x><y>99</y></pt></polygon></object><object><name>yellow</name><deleted>0</deleted><verified>0</verified><occluded>no</occluded><attributes></attributes><parts><hasparts></hasparts><ispartof></ispartof></parts><date>07-Jun-2018 14:50:31</date><id>37</id><type>bounding_box</type><polygon><username>anonymous</username><pt><x>645</x><y>95</y></pt><pt><x>629</x><y>95</y></pt><pt><x>629</x><y>114</y></pt><pt><x>645</x><y>114</y></pt></polygon></object><object><name>blue</name><deleted>0</deleted><verified>0</verified><occluded>no</occluded><attributes></attributes><parts><hasparts></hasparts><ispartof></ispartof></parts><date>07-Jun-2018 14:50:37</date><id>38</id><type>bounding_box</type><polygon><username>anonymous</username><pt><x>747</x><y>96</y></pt><pt><x>733</x><y>96</y></pt><pt><x>733</x><y>112</y></pt><pt><x>747</x><y>112</y></pt></polygon></object><object><name>yellow</name><deleted>0</deleted><verified>0</verified><occluded>no</occluded><attributes></attributes><parts><hasparts></hasparts><ispartof></ispartof></parts><date>07-Jun-2018 14:50:42</date><id>39</id><type>bounding_box</type><polygon><username>anonymous</username><pt><x>839</x><y>115</y></pt><pt><x>813</x><y>115</y></pt><pt><x>813</x><y>142</y></pt><pt><x>839</x><y>142</y></pt></polygon></object><object><name>yellow</name><deleted>0</deleted><verified>0</verified><occluded>no</occluded><attributes></attributes><parts><hasparts></hasparts><ispartof></ispartof></parts><date>07-Jun-2018 14:50:50</date><id>40</id><type>bounding_box</type><polygon><username>anonymous</username><pt><x>790</x><y>147</y></pt><pt><x>739</x><y>147</y></pt><pt><x>739</x><y>196</y></pt><pt><x>790</x><y>196</y></pt></polygon></object><object><name>yellow</name><deleted>0</deleted><verified>0</verified><occluded>no</occluded><attributes></attributes><parts><hasparts></hasparts><ispartof></ispartof></parts><date>07-Jun-2018 14:51:06</date><id>41</id><type>bounding_box</type><polygon><username>anonymous</username><pt><x>70</x><y>78</y></pt><pt><x>86</x><y>78</y></pt><pt><x>86</x><y>97</y></pt><pt><x>70</x><y>97</y></pt></polygon></object><object><name>blue</name><deleted>0</deleted><verified>0</verified><occluded>no</occluded><attributes></attributes><parts><hasparts></hasparts><ispartof></ispartof></parts><date>07-Jun-2018 14:51:12</date><id>42</id><type>bounding_box</type><polygon><username>anonymous</username><pt><x>49</x><y>103</y></pt><pt><x>78</x><y>103</y></pt><pt><x>78</x><y>137</y></pt><pt><x>49</x><y>137</y></pt></polygon></object><object><name>blue</name><deleted>0</deleted><verified>0</verified><occluded>no</occluded><attributes></attributes><parts><hasparts></hasparts><ispartof></ispartof></parts><date>07-Jun-2018 14:51:16</date><id>43</id><type>bounding_box</type><polygon><username>anonymous</username><pt><x>89</x><y>120</y></pt><pt><x>128</x><y>120</y></pt><pt><x>128</x><y>162</y></pt><pt><x>89</x><y>162</y></pt></polygon></object><object><name>yellow</name><deleted>0</deleted><verified>0</verified><occluded>no</occluded><attributes></attributes><parts><hasparts></hasparts><ispartof></ispartof></parts><date>07-Jun-2018 14:51:21</date><id>44</id><type>bounding_box</type><polygon><username>anonymous</username><pt><x>203</x><y>83</y></pt><pt><x>220</x><y>83</y></pt><pt><x>220</x><y>102</y></pt><pt><x>203</x><y>102</y></pt></polygon></object><object><name>yellow</name><deleted>0</deleted><verified>0</verified><occluded>no</occluded><attributes></attributes><parts><hasparts></hasparts><ispartof></ispartof></parts><date>07-Jun-2018 14:51:27</date><id>45</id><type>bounding_box</type><polygon><username>anonymous</username><pt><x>344</x><y>87</y></pt><pt><x>363</x><y>87</y></pt><pt><x>363</x><y>111</y></pt><pt><x>344</x><y>111</y></pt></polygon></object><object><name>yellow</name><deleted>0</deleted><verified>0</verified><occluded>no</occluded><attributes></attributes><parts><hasparts></hasparts><ispartof></ispartof></parts><date>07-Jun-2018 14:51:33</date><id>46</id><type>bounding_box</type><polygon><username>anonymous</username><pt><x>492</x><y>103</y></pt><pt><x>515</x><y>103</y></pt><pt><x>515</x><y>135</y></pt><pt><x>492</x><y>135</y></pt></polygon></object><imagesize><nrows>256</nrows><ncols>960</ncols></imagesize></annotation>