<annotation><filename>frame5451.jpg</filename><folder>batch_186</folder><source><sourceImage>The MIT-CSAIL database of objects and scenes</sourceImage><sourceAnnotation>LabelMe Webtool</sourceAnnotation></source><object><name>yellow</name><deleted>0</deleted><verified>0</verified><occluded>no</occluded><attributes></attributes><parts><hasparts></hasparts><ispartof></ispartof></parts><date>23-Jun-2018 21:44:15</date><id>0</id><type>bounding_box</type><polygon><username>anonymous</username><pt><x>2</x><y>75</y></pt><pt><x>11</x><y>75</y></pt><pt><x>11</x><y>61</y></pt><pt><x>2</x><y>61</y></pt></polygon></object><object><name>blue</name><deleted>0</deleted><verified>0</verified><occluded>no</occluded><attributes></attributes><parts><hasparts></hasparts><ispartof></ispartof></parts><date>23-Jun-2018 21:44:19</date><id>1</id><type>bounding_box</type><polygon><username>anonymous</username><pt><x>50</x><y>228</y></pt><pt><x>101</x><y>228</y></pt><pt><x>101</x><y>162</y></pt><pt><x>50</x><y>162</y></pt></polygon></object><object><name>blue</name><deleted>0</deleted><verified>0</verified><occluded>no</occluded><attributes></attributes><parts><hasparts></hasparts><ispartof></ispartof></parts><date>23-Jun-2018 21:44:25</date><id>2</id><type>bounding_box</type><polygon><username>anonymous</username><pt><x>88</x><y>81</y></pt><pt><x>99</x><y>81</y></pt><pt><x>99</x><y>66</y></pt><pt><x>88</x><y>66</y></pt></polygon></object><object><name>yellow</name><deleted>0</deleted><verified>0</verified><occluded>no</occluded><attributes></attributes><parts><hasparts></hasparts><ispartof></ispartof></parts><date>23-Jun-2018 21:44:29</date><id>3</id><type>bounding_box</type><polygon><username>anonymous</username><pt><x>163</x><y>75</y></pt><pt><x>172</x><y>75</y></pt><pt><x>172</x><y>60</y></pt><pt><x>163</x><y>60</y></pt></polygon></object><object><name>blue</name><deleted>0</deleted><verified>0</verified><occluded>no</occluded><attributes></attributes><parts><hasparts></hasparts><ispartof></ispartof></parts><date>23-Jun-2018 21:44:40</date><id>4</id><type>bounding_box</type><polygon><username>anonymous</username><pt><x>199</x><y>86</y></pt><pt><x>212</x><y>86</y></pt><pt><x>212</x><y>70</y></pt><pt><x>199</x><y>70</y></pt></polygon></object><object><name>orange_big</name><deleted>0</deleted><verified>0</verified><occluded>no</occluded><attributes></attributes><parts><hasparts></hasparts><ispartof></ispartof></parts><date>23-Jun-2018 21:44:45</date><id>5</id><type>bounding_box</type><polygon><username>anonymous</username><pt><x>237</x><y>163</y></pt><pt><x>280</x><y>163</y></pt><pt><x>280</x><y>98</y></pt><pt><x>237</x><y>98</y></pt></polygon></object><object><name>blue</name><deleted>0</deleted><verified>0</verified><occluded>no</occluded><attributes></attributes><parts><hasparts></hasparts><ispartof></ispartof></parts><date>23-Jun-2018 21:44:50</date><id>6</id><type>bounding_box</type><polygon><username>anonymous</username><pt><x>274</x><y>93</y></pt><pt><x>286</x><y>93</y></pt><pt><x>286</x><y>74</y></pt><pt><x>274</x><y>74</y></pt></polygon></object><object><name>yellow</name><deleted>0</deleted><verified>0</verified><occluded>no</occluded><attributes></attributes><parts><hasparts></hasparts><ispartof></ispartof></parts><date>23-Jun-2018 21:45:09</date><id>7</id><type>bounding_box</type><polygon><username>anonymous</username><pt><x>296</x><y>78</y></pt><pt><x>307</x><y>78</y></pt><pt><x>307</x><y>65</y></pt><pt><x>296</x><y>65</y></pt></polygon></object><object><name>blue</name><deleted>0</deleted><verified>0</verified><occluded>no</occluded><attributes></attributes><parts><hasparts></hasparts><ispartof></ispartof></parts><date>23-Jun-2018 21:45:14</date><id>8</id><type>bounding_box</type><polygon><username>anonymous</username><pt><x>322</x><y>106</y></pt><pt><x>335</x><y>106</y></pt><pt><x>335</x><y>83</y></pt><pt><x>322</x><y>83</y></pt></polygon></object><object><name>blue</name><deleted>0</deleted><verified>0</verified><occluded>no</occluded><attributes></attributes><parts><hasparts></hasparts><ispartof></ispartof></parts><date>23-Jun-2018 21:45:18</date><id>9</id><type>bounding_box</type><polygon><username>anonymous</username><pt><x>310</x><y>134</y></pt><pt><x>329</x><y>134</y></pt><pt><x>329</x><y>105</y></pt><pt><x>310</x><y>105</y></pt></polygon></object><object><name>orange_big</name><deleted>0</deleted><verified>0</verified><occluded>no</occluded><attributes></attributes><parts><hasparts></hasparts><ispartof></ispartof></parts><date>23-Jun-2018 21:45:23</date><id>10</id><type>bounding_box</type><polygon><username>anonymous</username><pt><x>350</x><y>117</y></pt><pt><x>329</x><y>117</y></pt><pt><x>329</x><y>77</y></pt><pt><x>350</x><y>77</y></pt></polygon></object><object><name>orange_big</name><deleted>1</deleted><verified>0</verified><occluded>no</occluded><attributes></attributes><parts><hasparts></hasparts><ispartof></ispartof></parts><date>23-Jun-2018 21:45:33</date><id>11</id><type>bounding_box</type><polygon><username>anonymous</username><pt><x>401</x><y>85</y></pt><pt><x>409</x><y>85</y></pt><pt><x>409</x><y>70</y></pt><pt><x>401</x><y>70</y></pt></polygon></object><object><name>yellow</name><deleted>0</deleted><verified>0</verified><occluded>no</occluded><attributes></attributes><parts><hasparts></hasparts><ispartof></ispartof></parts><date>23-Jun-2018 21:45:41</date><id>12</id><type>bounding_box</type><polygon><username>anonymous</username><pt><x>400</x><y>86</y></pt><pt><x>411</x><y>86</y></pt><pt><x>411</x><y>70</y></pt><pt><x>400</x><y>70</y></pt></polygon></object><object><name>orange small</name><deleted>0</deleted><verified>0</verified><occluded>no</occluded><attributes></attributes><parts><hasparts></hasparts><ispartof></ispartof></parts><date>23-Jun-2018 21:45:46</date><id>13</id><type>bounding_box</type><polygon><username>anonymous</username><pt><x>419</x><y>79</y></pt><pt><x>412</x><y>79</y></pt><pt><x>412</x><y>67</y></pt><pt><x>419</x><y>67</y></pt></polygon></object><object><name>orange small</name><deleted>0</deleted><verified>0</verified><occluded>no</occluded><attributes></attributes><parts><hasparts></hasparts><ispartof></ispartof></parts><date>23-Jun-2018 21:45:50</date><id>14</id><type>bounding_box</type><polygon><username>anonymous</username><pt><x>425</x><y>73</y></pt><pt><x>419</x><y>73</y></pt><pt><x>419</x><y>64</y></pt><pt><x>425</x><y>64</y></pt></polygon></object><object><name>orange small</name><deleted>0</deleted><verified>0</verified><occluded>no</occluded><attributes></attributes><parts><hasparts></hasparts><ispartof></ispartof></parts><date>23-Jun-2018 21:45:56</date><id>15</id><type>bounding_box</type><polygon><username>anonymous</username><pt><x>429</x><y>72</y></pt><pt><x>422</x><y>72</y></pt><pt><x>422</x><y>61</y></pt><pt><x>429</x><y>61</y></pt></polygon></object><object><name>orange small</name><deleted>0</deleted><verified>0</verified><occluded>no</occluded><attributes></attributes><parts><hasparts></hasparts><ispartof></ispartof></parts><date>23-Jun-2018 21:46:03</date><id>16</id><type>bounding_box</type><polygon><username>anonymous</username><pt><x>433</x><y>69</y></pt><pt><x>427</x><y>69</y></pt><pt><x>427</x><y>59</y></pt><pt><x>433</x><y>59</y></pt></polygon></object><object><name>orange small</name><deleted>0</deleted><verified>0</verified><occluded>no</occluded><attributes></attributes><parts><hasparts></hasparts><ispartof></ispartof></parts><date>23-Jun-2018 21:46:08</date><id>17</id><type>bounding_box</type><polygon><username>anonymous</username><pt><x>438</x><y>65</y></pt><pt><x>433</x><y>65</y></pt><pt><x>433</x><y>56</y></pt><pt><x>438</x><y>56</y></pt></polygon></object><object><name>orange small</name><deleted>0</deleted><verified>0</verified><occluded>no</occluded><attributes></attributes><parts><hasparts></hasparts><ispartof></ispartof></parts><date>23-Jun-2018 21:46:13</date><id>18</id><type>bounding_box</type><polygon><username>anonymous</username><pt><x>443</x><y>64</y></pt><pt><x>437</x><y>64</y></pt><pt><x>437</x><y>55</y></pt><pt><x>443</x><y>55</y></pt></polygon></object><object><name>orange small</name><deleted>0</deleted><verified>0</verified><occluded>no</occluded><attributes></attributes><parts><hasparts></hasparts><ispartof></ispartof></parts><date>23-Jun-2018 21:46:20</date><id>19</id><type>bounding_box</type><polygon><username>anonymous</username><pt><x>463</x><y>65</y></pt><pt><x>470</x><y>65</y></pt><pt><x>470</x><y>56</y></pt><pt><x>463</x><y>56</y></pt></polygon></object><object><name>orange small</name><deleted>0</deleted><verified>0</verified><occluded>no</occluded><attributes></attributes><parts><hasparts></hasparts><ispartof></ispartof></parts><date>23-Jun-2018 21:46:35</date><id>20</id><type>bounding_box</type><polygon><username>anonymous</username><pt><x>489</x><y>64</y></pt><pt><x>496</x><y>64</y></pt><pt><x>496</x><y>56</y></pt><pt><x>489</x><y>56</y></pt></polygon></object><object><name>orange small</name><deleted>0</deleted><verified>0</verified><occluded>no</occluded><attributes></attributes><parts><hasparts></hasparts><ispartof></ispartof></parts><date>23-Jun-2018 21:46:39</date><id>21</id><type>bounding_box</type><polygon><username>anonymous</username><pt><x>520</x><y>80</y></pt><pt><x>527</x><y>80</y></pt><pt><x>527</x><y>69</y></pt><pt><x>520</x><y>69</y></pt></polygon></object><object><name>blue</name><deleted>0</deleted><verified>0</verified><occluded>no</occluded><attributes></attributes><parts><hasparts></hasparts><ispartof></ispartof></parts><date>23-Jun-2018 21:46:44</date><id>22</id><type>bounding_box</type><polygon><username>anonymous</username><pt><x>522</x><y>85</y></pt><pt><x>530</x><y>85</y></pt><pt><x>530</x><y>73</y></pt><pt><x>522</x><y>73</y></pt></polygon></object><object><name>orange_big</name><deleted>0</deleted><verified>0</verified><occluded>no</occluded><attributes></attributes><parts><hasparts></hasparts><ispartof></ispartof></parts><date>23-Jun-2018 21:46:52</date><id>23</id><type>bounding_box</type><polygon><username>anonymous</username><pt><x>583</x><y>119</y></pt><pt><x>606</x><y>119</y></pt><pt><x>606</x><y>82</y></pt><pt><x>583</x><y>82</y></pt></polygon></object><object><name>yellow</name><deleted>0</deleted><verified>0</verified><occluded>no</occluded><attributes></attributes><parts><hasparts></hasparts><ispartof></ispartof></parts><date>23-Jun-2018 21:46:57</date><id>24</id><type>bounding_box</type><polygon><username>anonymous</username><pt><x>596</x><y>136</y></pt><pt><x>620</x><y>136</y></pt><pt><x>620</x><y>105</y></pt><pt><x>596</x><y>105</y></pt></polygon></object><object><name>orange_big</name><deleted>0</deleted><verified>0</verified><occluded>no</occluded><attributes></attributes><parts><hasparts></hasparts><ispartof></ispartof></parts><date>23-Jun-2018 21:47:03</date><id>25</id><type>bounding_box</type><polygon><username>anonymous</username><pt><x>704</x><y>170</y></pt><pt><x>663</x><y>170</y></pt><pt><x>663</x><y>105</y></pt><pt><x>704</x><y>105</y></pt></polygon></object><object><name>yellow</name><deleted>0</deleted><verified>0</verified><occluded>no</occluded><attributes></attributes><parts><hasparts></hasparts><ispartof></ispartof></parts><date>23-Jun-2018 21:47:07</date><id>26</id><type>bounding_box</type><polygon><username>anonymous</username><pt><x>874</x><y>224</y></pt><pt><x>826</x><y>224</y></pt><pt><x>826</x><y>164</y></pt><pt><x>874</x><y>164</y></pt></polygon></object><object><name>blue</name><deleted>0</deleted><verified>0</verified><occluded>no</occluded><attributes></attributes><parts><hasparts></hasparts><ispartof></ispartof></parts><date>23-Jun-2018 21:47:15</date><id>27</id><type>bounding_box</type><polygon><username>anonymous</username><pt><x>617</x><y>80</y></pt><pt><x>626</x><y>80</y></pt><pt><x>626</x><y>67</y></pt><pt><x>617</x><y>67</y></pt></polygon></object><object><name>yellow</name><deleted>0</deleted><verified>0</verified><occluded>no</occluded><attributes></attributes><parts><hasparts></hasparts><ispartof></ispartof></parts><date>23-Jun-2018 21:47:20</date><id>28</id><type>bounding_box</type><polygon><username>anonymous</username><pt><x>631</x><y>95</y></pt><pt><x>643</x><y>95</y></pt><pt><x>643</x><y>78</y></pt><pt><x>631</x><y>78</y></pt></polygon></object><object><name>yellow</name><deleted>0</deleted><verified>0</verified><occluded>no</occluded><attributes></attributes><parts><hasparts></hasparts><ispartof></ispartof></parts><date>23-Jun-2018 21:47:24</date><id>29</id><type>bounding_box</type><polygon><username>anonymous</username><pt><x>704</x><y>90</y></pt><pt><x>716</x><y>90</y></pt><pt><x>716</x><y>75</y></pt><pt><x>704</x><y>75</y></pt></polygon></object><object><name>blue</name><deleted>0</deleted><verified>0</verified><occluded>no</occluded><attributes></attributes><parts><hasparts></hasparts><ispartof></ispartof></parts><date>23-Jun-2018 21:47:30</date><id>30</id><type>bounding_box</type><polygon><username>anonymous</username><pt><x>731</x><y>78</y></pt><pt><x>739</x><y>78</y></pt><pt><x>739</x><y>67</y></pt><pt><x>731</x><y>67</y></pt></polygon></object><object><name>yellow</name><deleted>0</deleted><verified>0</verified><occluded>no</occluded><attributes></attributes><parts><hasparts></hasparts><ispartof></ispartof></parts><date>23-Jun-2018 21:47:35</date><id>31</id><type>bounding_box</type><polygon><username>anonymous</username><pt><x>794</x><y>89</y></pt><pt><x>805</x><y>89</y></pt><pt><x>805</x><y>74</y></pt><pt><x>794</x><y>74</y></pt></polygon></object><object><name>blue</name><deleted>0</deleted><verified>0</verified><occluded>no</occluded><attributes></attributes><parts><hasparts></hasparts><ispartof></ispartof></parts><date>23-Jun-2018 21:47:42</date><id>32</id><type>bounding_box</type><polygon><username>anonymous</username><pt><x>864</x><y>81</y></pt><pt><x>873</x><y>81</y></pt><pt><x>873</x><y>68</y></pt><pt><x>864</x><y>68</y></pt></polygon></object><object><name>yellow</name><deleted>0</deleted><verified>0</verified><occluded>no</occluded><attributes></attributes><parts><hasparts></hasparts><ispartof></ispartof></parts><date>23-Jun-2018 21:47:46</date><id>33</id><type>bounding_box</type><polygon><username>anonymous</username><pt><x>910</x><y>91</y></pt><pt><x>922</x><y>91</y></pt><pt><x>922</x><y>76</y></pt><pt><x>910</x><y>76</y></pt></polygon></object><imagesize><nrows>256</nrows><ncols>960</ncols></imagesize></annotation>