<annotation><filename>frame4571.jpg</filename><folder>batch_98</folder><source><sourceImage>The MIT-CSAIL database of objects and scenes</sourceImage><sourceAnnotation>LabelMe Webtool</sourceAnnotation></source><object><name>blue</name><deleted>0</deleted><verified>0</verified><occluded>no</occluded><attributes></attributes><parts><hasparts></hasparts><ispartof></ispartof></parts><date>24-Jun-2018 20:25:10</date><id>0</id><type>bounding_box</type><polygon><username>anonymous</username><pt><x>176</x><y>138</y></pt><pt><x>215</x><y>138</y></pt><pt><x>215</x><y>191</y></pt><pt><x>176</x><y>191</y></pt></polygon></object><object><name>blue</name><deleted>0</deleted><verified>0</verified><occluded>no</occluded><attributes></attributes><parts><hasparts></hasparts><ispartof></ispartof></parts><date>24-Jun-2018 20:25:15</date><id>1</id><type>bounding_box</type><polygon><username>anonymous</username><pt><x>388</x><y>107</y></pt><pt><x>411</x><y>107</y></pt><pt><x>411</x><y>138</y></pt><pt><x>388</x><y>138</y></pt></polygon></object><object><name>blue</name><deleted>0</deleted><verified>0</verified><occluded>no</occluded><attributes></attributes><parts><hasparts></hasparts><ispartof></ispartof></parts><date>24-Jun-2018 20:25:21</date><id>2</id><type>bounding_box</type><polygon><username>anonymous</username><pt><x>474</x><y>94</y></pt><pt><x>488</x><y>94</y></pt><pt><x>488</x><y>121</y></pt><pt><x>474</x><y>121</y></pt></polygon></object><object><name>blue</name><deleted>0</deleted><verified>0</verified><occluded>no</occluded><attributes></attributes><parts><hasparts></hasparts><ispartof></ispartof></parts><date>24-Jun-2018 20:25:26</date><id>3</id><type>bounding_box</type><polygon><username>anonymous</username><pt><x>529</x><y>89</y></pt><pt><x>542</x><y>89</y></pt><pt><x>542</x><y>110</y></pt><pt><x>529</x><y>110</y></pt></polygon></object><object><name>blue</name><deleted>0</deleted><verified>0</verified><occluded>no</occluded><attributes></attributes><parts><hasparts></hasparts><ispartof></ispartof></parts><date>24-Jun-2018 20:25:30</date><id>4</id><type>bounding_box</type><polygon><username>anonymous</username><pt><x>577</x><y>85</y></pt><pt><x>589</x><y>85</y></pt><pt><x>589</x><y>103</y></pt><pt><x>577</x><y>103</y></pt></polygon></object><object><name>blue</name><deleted>0</deleted><verified>0</verified><occluded>no</occluded><attributes></attributes><parts><hasparts></hasparts><ispartof></ispartof></parts><date>24-Jun-2018 20:25:34</date><id>5</id><type>bounding_box</type><polygon><username>anonymous</username><pt><x>616</x><y>82</y></pt><pt><x>627</x><y>82</y></pt><pt><x>627</x><y>98</y></pt><pt><x>616</x><y>98</y></pt></polygon></object><object><name>blue</name><deleted>0</deleted><verified>0</verified><occluded>no</occluded><attributes></attributes><parts><hasparts></hasparts><ispartof></ispartof></parts><date>24-Jun-2018 20:25:40</date><id>6</id><type>bounding_box</type><polygon><username>anonymous</username><pt><x>662</x><y>79</y></pt><pt><x>673</x><y>79</y></pt><pt><x>673</x><y>96</y></pt><pt><x>662</x><y>96</y></pt></polygon></object><object><name>yellow</name><deleted>0</deleted><verified>0</verified><occluded>no</occluded><attributes></attributes><parts><hasparts></hasparts><ispartof></ispartof></parts><date>24-Jun-2018 20:25:44</date><id>7</id><type>bounding_box</type><polygon><username>anonymous</username><pt><x>777</x><y>156</y></pt><pt><x>819</x><y>156</y></pt><pt><x>819</x><y>214</y></pt><pt><x>777</x><y>214</y></pt></polygon></object><object><name>yellow</name><deleted>0</deleted><verified>0</verified><occluded>no</occluded><attributes></attributes><parts><hasparts></hasparts><ispartof></ispartof></parts><date>24-Jun-2018 20:25:49</date><id>8</id><type>bounding_box</type><polygon><username>anonymous</username><pt><x>721</x><y>121</y></pt><pt><x>749</x><y>121</y></pt><pt><x>749</x><y>158</y></pt><pt><x>721</x><y>158</y></pt></polygon></object><object><name>yellow</name><deleted>0</deleted><verified>0</verified><occluded>no</occluded><attributes></attributes><parts><hasparts></hasparts><ispartof></ispartof></parts><date>24-Jun-2018 20:25:53</date><id>9</id><type>bounding_box</type><polygon><username>anonymous</username><pt><x>711</x><y>103</y></pt><pt><x>728</x><y>103</y></pt><pt><x>728</x><y>127</y></pt><pt><x>711</x><y>127</y></pt></polygon></object><object><name>yellow</name><deleted>0</deleted><verified>0</verified><occluded>no</occluded><attributes></attributes><parts><hasparts></hasparts><ispartof></ispartof></parts><date>24-Jun-2018 20:25:59</date><id>10</id><type>bounding_box</type><polygon><username>anonymous</username><pt><x>712</x><y>92</y></pt><pt><x>727</x><y>92</y></pt><pt><x>727</x><y>115</y></pt><pt><x>712</x><y>115</y></pt></polygon></object><object><name>yellow</name><deleted>0</deleted><verified>0</verified><occluded>no</occluded><attributes></attributes><parts><hasparts></hasparts><ispartof></ispartof></parts><date>24-Jun-2018 20:26:06</date><id>11</id><type>bounding_box</type><polygon><username>anonymous</username><pt><x>730</x><y>86</y></pt><pt><x>741</x><y>86</y></pt><pt><x>741</x><y>100</y></pt><pt><x>730</x><y>100</y></pt></polygon></object><imagesize><nrows>256</nrows><ncols>960</ncols></imagesize></annotation>