<annotation><filename>frame4165.jpg</filename><folder>batch_58</folder><source><sourceImage>The MIT-CSAIL database of objects and scenes</sourceImage><sourceAnnotation>LabelMe Webtool</sourceAnnotation></source><object><name>blue</name><deleted>0</deleted><verified>0</verified><occluded>no</occluded><attributes></attributes><parts><hasparts></hasparts><ispartof></ispartof></parts><date>08-Jun-2018 09:05:19</date><id>0</id><type>bounding_box</type><polygon><username>anonymous</username><pt><x>340</x><y>221</y></pt><pt><x>381</x><y>221</y></pt><pt><x>381</x><y>164</y></pt><pt><x>340</x><y>164</y></pt></polygon></object><object><name>blue</name><deleted>0</deleted><verified>0</verified><occluded>no</occluded><attributes></attributes><parts><hasparts></hasparts><ispartof></ispartof></parts><date>08-Jun-2018 09:05:26</date><id>1</id><type>bounding_box</type><polygon><username>anonymous</username><pt><x>502</x><y>143</y></pt><pt><x>526</x><y>143</y></pt><pt><x>526</x><y>112</y></pt><pt><x>502</x><y>112</y></pt></polygon></object><object><name>blue</name><deleted>0</deleted><verified>0</verified><occluded>no</occluded><attributes></attributes><parts><hasparts></hasparts><ispartof></ispartof></parts><date>08-Jun-2018 09:05:32</date><id>2</id><type>bounding_box</type><polygon><username>anonymous</username><pt><x>624</x><y>109</y></pt><pt><x>637</x><y>109</y></pt><pt><x>637</x><y>90</y></pt><pt><x>624</x><y>90</y></pt></polygon></object><object><name>blue</name><deleted>0</deleted><verified>0</verified><occluded>no</occluded><attributes></attributes><parts><hasparts></hasparts><ispartof></ispartof></parts><date>08-Jun-2018 09:05:43</date><id>3</id><type>bounding_box</type><polygon><username>anonymous</username><pt><x>694</x><y>96</y></pt><pt><x>704</x><y>96</y></pt><pt><x>704</x><y>82</y></pt><pt><x>694</x><y>82</y></pt></polygon></object><object><name>blue</name><deleted>0</deleted><verified>0</verified><occluded>no</occluded><attributes></attributes><parts><hasparts></hasparts><ispartof></ispartof></parts><date>08-Jun-2018 09:05:55</date><id>4</id><type>bounding_box</type><polygon><username>anonymous</username><pt><x>726</x><y>91</y></pt><pt><x>733</x><y>91</y></pt><pt><x>733</x><y>80</y></pt><pt><x>726</x><y>80</y></pt></polygon></object><object><name>blue</name><deleted>0</deleted><verified>0</verified><occluded>no</occluded><attributes></attributes><parts><hasparts></hasparts><ispartof></ispartof></parts><date>08-Jun-2018 09:06:04</date><id>5</id><type>bounding_box</type><polygon><username>anonymous</username><pt><x>752</x><y>88</y></pt><pt><x>758</x><y>88</y></pt><pt><x>758</x><y>78</y></pt><pt><x>752</x><y>78</y></pt></polygon></object><object><name>blue</name><deleted>0</deleted><verified>0</verified><occluded>no</occluded><attributes></attributes><parts><hasparts></hasparts><ispartof></ispartof></parts><date>08-Jun-2018 09:06:10</date><id>6</id><type>bounding_box</type><polygon><username>anonymous</username><pt><x>769</x><y>87</y></pt><pt><x>775</x><y>87</y></pt><pt><x>775</x><y>78</y></pt><pt><x>769</x><y>78</y></pt></polygon></object><object><name>yellow</name><deleted>0</deleted><verified>0</verified><occluded>no</occluded><attributes></attributes><parts><hasparts></hasparts><ispartof></ispartof></parts><date>08-Jun-2018 09:06:23</date><id>7</id><type>bounding_box</type><polygon><username>anonymous</username><pt><x>858</x><y>95</y></pt><pt><x>868</x><y>95</y></pt><pt><x>868</x><y>84</y></pt><pt><x>858</x><y>84</y></pt></polygon></object><object><name>yellow</name><deleted>0</deleted><verified>0</verified><occluded>no</occluded><attributes></attributes><parts><hasparts></hasparts><ispartof></ispartof></parts><date>08-Jun-2018 09:06:29</date><id>8</id><type>bounding_box</type><polygon><username>anonymous</username><pt><x>861</x><y>104</y></pt><pt><x>873</x><y>104</y></pt><pt><x>873</x><y>91</y></pt><pt><x>861</x><y>91</y></pt></polygon></object><object><name>yellow</name><deleted>0</deleted><verified>0</verified><occluded>no</occluded><attributes></attributes><parts><hasparts></hasparts><ispartof></ispartof></parts><date>08-Jun-2018 09:06:36</date><id>9</id><type>bounding_box</type><polygon><username>anonymous</username><pt><x>879</x><y>124</y></pt><pt><x>897</x><y>124</y></pt><pt><x>897</x><y>103</y></pt><pt><x>879</x><y>103</y></pt></polygon></object><imagesize><nrows>256</nrows><ncols>960</ncols></imagesize></annotation>