<annotation><filename>frame3904.jpg</filename><folder>batch_32</folder><source><sourceImage>The MIT-CSAIL database of objects and scenes</sourceImage><sourceAnnotation>LabelMe Webtool</sourceAnnotation></source><object><name>blue</name><deleted>0</deleted><verified>0</verified><occluded>no</occluded><attributes></attributes><parts><hasparts></hasparts><ispartof></ispartof></parts><date>04-Jun-2018 13:42:45</date><id>0</id><type>bounding_box</type><polygon><username>anonymous</username><pt><x>193</x><y>128</y></pt><pt><x>217</x><y>128</y></pt><pt><x>217</x><y>168</y></pt><pt><x>193</x><y>168</y></pt></polygon></object><object><name>blue</name><deleted>0</deleted><verified>0</verified><occluded>no</occluded><attributes></attributes><parts><hasparts></hasparts><ispartof></ispartof></parts><date>04-Jun-2018 13:42:51</date><id>1</id><type>bounding_box</type><polygon><username>anonymous</username><pt><x>445</x><y>98</y></pt><pt><x>456</x><y>98</y></pt><pt><x>456</x><y>118</y></pt><pt><x>445</x><y>118</y></pt></polygon></object><object><name>blue</name><deleted>0</deleted><verified>0</verified><occluded>no</occluded><attributes></attributes><parts><hasparts></hasparts><ispartof></ispartof></parts><date>04-Jun-2018 13:43:03</date><id>2</id><type>bounding_box</type><polygon><username>anonymous</username><pt><x>549</x><y>94</y></pt><pt><x>556</x><y>94</y></pt><pt><x>556</x><y>110</y></pt><pt><x>549</x><y>110</y></pt></polygon></object><object><name>blue</name><deleted>0</deleted><verified>0</verified><occluded>no</occluded><attributes></attributes><parts><hasparts></hasparts><ispartof></ispartof></parts><date>04-Jun-2018 13:43:10</date><id>3</id><type>bounding_box</type><polygon><username>anonymous</username><pt><x>614</x><y>93</y></pt><pt><x>621</x><y>93</y></pt><pt><x>621</x><y>106</y></pt><pt><x>614</x><y>106</y></pt></polygon></object><object><name>yellow</name><deleted>0</deleted><verified>0</verified><occluded>no</occluded><attributes></attributes><parts><hasparts></hasparts><ispartof></ispartof></parts><date>04-Jun-2018 13:43:16</date><id>4</id><type>bounding_box</type><polygon><username>anonymous</username><pt><x>768</x><y>117</y></pt><pt><x>785</x><y>117</y></pt><pt><x>785</x><y>147</y></pt><pt><x>768</x><y>147</y></pt></polygon></object><object><name>yellow</name><deleted>0</deleted><verified>0</verified><occluded>no</occluded><attributes></attributes><parts><hasparts></hasparts><ispartof></ispartof></parts><date>04-Jun-2018 13:43:21</date><id>5</id><type>bounding_box</type><polygon><username>anonymous</username><pt><x>783</x><y>104</y></pt><pt><x>794</x><y>104</y></pt><pt><x>794</x><y>124</y></pt><pt><x>783</x><y>124</y></pt></polygon></object><object><name>yellow</name><deleted>0</deleted><verified>0</verified><occluded>no</occluded><attributes></attributes><parts><hasparts></hasparts><ispartof></ispartof></parts><date>04-Jun-2018 13:43:26</date><id>6</id><type>bounding_box</type><polygon><username>anonymous</username><pt><x>803</x><y>101</y></pt><pt><x>812</x><y>101</y></pt><pt><x>812</x><y>116</y></pt><pt><x>803</x><y>116</y></pt></polygon></object><object><name>yellow</name><deleted>0</deleted><verified>0</verified><occluded>no</occluded><attributes></attributes><parts><hasparts></hasparts><ispartof></ispartof></parts><date>04-Jun-2018 13:43:33</date><id>7</id><type>bounding_box</type><polygon><username>anonymous</username><pt><x>771</x><y>91</y></pt><pt><x>778</x><y>91</y></pt><pt><x>778</x><y>104</y></pt><pt><x>771</x><y>104</y></pt></polygon></object><imagesize><nrows>256</nrows><ncols>960</ncols></imagesize></annotation>